{"sex":1,"bz":{"0":"甲","1":"戌","2":"庚","3":"午","6":"壬","7":"戌","4":"癸","5":"未","8":"1994年五月十八 戌时"},"tdbz":[],"ss":["伤官","正印","日主","劫财"],"cg":[["戊","辛","丁"],["丁","己"],["己","丁","乙"],["戊","辛","丁"]],"cgss":[["正官","偏印","偏财"],["偏财","七杀"],["七杀","偏财","食神"],["正官","偏印","偏财"]],"kw":["申酉","戌亥","申酉","子丑"],"xy":["衰","绝","墓","衰"],"zz":["养","沐浴","墓","冠带"],"ny":["山头火","路旁土","杨柳木","大海水"],"dayun":["辛未","壬申","癸酉","甲戌","乙亥","丙子","丁丑","戊寅","己卯","庚辰","辛巳","壬午"],"xiaoyun":["癸亥","甲子","乙丑","丙寅","丁卯","戊辰","己巳","庚午","辛未","壬申","癸酉","甲戌","乙亥","丙子","丁丑","戊寅","己卯","庚辰","辛巳","壬午","癸未","甲申","乙酉","丙戌","丁亥","戊子","己丑","庚寅","辛卯","壬辰","癸巳","甲午","乙未","丙申","丁酉","戊戌","己亥","庚子","辛丑","壬寅","癸卯","甲辰","乙巳","丙午","丁未","戊申","己酉","庚戌","辛亥","壬子","癸丑","甲寅","乙卯","丙辰","丁巳","戊午","己未","庚申","辛酉","壬戌","癸亥","甲子","乙丑","丙寅","丁卯","戊辰","己巳","庚午","辛未","壬申","癸酉","甲戌","乙亥","丙子","丁丑","戊寅","己卯","庚辰","辛巳","壬午","癸未","甲申","乙酉","丙戌","丁亥","戊子","己丑","庚寅","辛卯","壬辰","癸巳","甲午","乙未","丙申","丁酉","戊戌","己亥","庚子","辛丑","壬寅","癸卯","甲辰","乙巳","丙午","丁未","戊申","己酉","庚戌","辛亥","壬子"],"qiyunsui":5,"qiyunarr":[3,7,11,14,44,5],"jiaoyun":"逢戊、癸年 立春后3天 交大运","szshensha":[["国印贵人"],["太极贵人","将星"],["天乙贵人","德秀贵人","十灵日","童子煞","寡宿","披麻"],["国印贵人","童子煞","华盖"],[]],"dyshensha":[["辛未",["天乙贵人","月德合","寡宿","披麻","华盖"]],["壬申",["太极贵人","国印贵人","红艳煞","空亡","驿马","吊客","劫煞"]],["癸酉",["德秀贵人","空亡"]],["甲戌",["国印贵人","华盖","天罗"]],["乙亥",["天罗地网","天德贵人","羊刃","劫煞","孤辰","天喜","天罗"]],["丙子",["太极贵人","福星贵人","月德贵人","德秀贵人","禄神","灾煞","丧门","桃花"]],["丁丑",["天乙贵人","福星贵人","德秀贵人","勾绞煞"]],["戊寅",["福星贵人","德秀贵人","天德合","金舆","流霞","亡神","学堂"]],["己卯",["天乙贵人","文昌贵人","天厨贵人","福星贵人","桃花","血刃","将星"]],["庚辰",["金舆"]],["辛巳",["文昌贵人","天厨贵人","天乙贵人","太极贵人","月德合","飞刃","亡神","红鸾","元辰","天医","驿马","词馆"]],["壬午",["太极贵人","将星"]]],"taixi":"戊午","taiyuan":"辛酉","minggong":"丁丑","shenggong":"己巳","taixi_nayin":"天上火","taiyuan_nayin":"石榴木","minggong_nayin":"涧下水","shenggong_nayin":"大林木","kongwang":"申酉","runtime":"4ms"}