{"sex":0,"bz":{"0":"己","1":"亥","2":"丁","3":"卯","6":"庚","7":"子","4":"壬","5":"子","8":"1959年二月廿三 子时"},"tdbz":[],"ss":["正官","正财","日主","偏印"],"cg":[["壬","甲"],["乙"],["癸"],["癸"]],"cgss":[["比肩","食神"],["伤官"],["劫财"],["劫财"]],"kw":["辰巳","戌亥","寅卯","辰巳"],"xy":["临官","死","帝旺","帝旺"],"zz":["胎","病","帝旺","死"],"ny":["平地木","炉中火","桑柘木","壁上土"],"dayun":["戊辰","己巳","庚午","辛未","壬申","癸酉","甲戌","乙亥","丙子","丁丑","戊寅","己卯"],"xiaoyun":["辛丑","壬寅","癸卯","甲辰","乙巳","丙午","丁未","戊申","己酉","庚戌","辛亥","壬子","癸丑","甲寅","乙卯","丙辰","丁巳","戊午","己未","庚申","辛酉","壬戌","癸亥","甲子","乙丑","丙寅","丁卯","戊辰","己巳","庚午","辛未","壬申","癸酉","甲戌","乙亥","丙子","丁丑","戊寅","己卯","庚辰","辛巳","壬午","癸未","甲申","乙酉","丙戌","丁亥","戊子","己丑","庚寅","辛卯","壬辰","癸巳","甲午","乙未","丙申","丁酉","戊戌","己亥","庚子","辛丑","壬寅","癸卯","甲辰","乙巳","丙午","丁未","戊申","己酉","庚戌","辛亥","壬子","癸丑","甲寅","乙卯","丙辰","丁巳","戊午","己未","庚申","辛酉","壬戌","癸亥","甲子","乙丑","丙寅","丁卯","戊辰","己巳","庚午","辛未","壬申","癸酉","甲戌","乙亥","丙子","丁丑","戊寅","己卯","庚辰","辛巳","壬午","癸未","甲申","乙酉","丙戌","丁亥","戊子","己丑","庚寅"],"qiyunsui":3,"qiyunarr":[1,11,20,6,4,3],"jiaoyun":"逢辛、丙年 惊蛰后17天 交大运","szshensha":[["月德合","禄神","流霞","亡神"],["天乙贵人","德秀贵人","空亡","将星"],["天乙贵人","德秀贵人","九丑日","孤鸾煞","红艳煞","童子煞","羊刃","桃花"],["天乙贵人","红艳煞","童子煞","羊刃","桃花","将星"],[]],"dyshensha":[["戊辰",["太极贵人","福星贵人","空亡","红鸾","华盖"]],["己巳",["天乙贵人","太极贵人","月德合","天德合","空亡","驿马","劫煞"]],["庚午",["飞刃","元辰"]],["辛未",["太极贵人","福星贵人","国印贵人","华盖","血刃"]],["壬申",["天乙贵人","太极贵人","德秀贵人","天德贵人","金舆","劫煞","披麻"]],["癸酉",["文昌贵人","天厨贵人","灾煞","吊客","桃花"]],["甲戌",["太极贵人","天罗地网","月德贵人","德秀贵人","寡宿","天喜"]],["乙亥",["德秀贵人","禄神","流霞","亡神","学堂"]],["丙子",["天乙贵人","红艳煞","羊刃","桃花","将星"]],["丁丑",["太极贵人","德秀贵人","金舆","丧门"]],["戊寅",["国印贵人","文昌贵人","天厨贵人","勾绞煞","空亡","亡神","孤辰","天医","驿马","词馆"]],["己卯",["天乙贵人","月德合","空亡","将星"]]],"taixi":"丁丑","taiyuan":"戊午","minggong":"丙寅","shenggong":"戊辰","taixi_nayin":"涧下水","taiyuan_nayin":"天上火","minggong_nayin":"炉中火","shenggong_nayin":"大林木","kongwang":"寅卯","runtime":"3ms","gzrelation":[["丁壬合化木,合化木,丁_壬,"],["亥卯半合木局,半合木局,,亥_卯","子卯相刑,刑,,子_卯"]]}